{
	"_id": "5e1568f91411ab41cbd81450",
	"type": "form",
	"tags": [],
	"owner": "5ddfaa682859774314661851",
	"components": [{
		"label": "ApproverName",
		"calculateValue": "if (data.privileges){\n  if(data.privileges['MANAGE_POLICY_APPROVAL_WRITE'] !== null && data.privileges['MANAGE_POLICY_APPROVAL_WRITE']){\n    value = data['userprofile'].name;\n  }\n}",
		"key": "approverName",
		"type": "hidden",
		"input": true,
		"tableView": false,
		"hideOnChildrenHidden": false,
		"placeholder": "",
		"prefix": "",
		"customClass": "",
		"suffix": "",
		"multiple": false,
		"defaultValue": null,
		"protected": false,
		"unique": false,
		"persistent": true,
		"hidden": false,
		"clearOnHide": true,
		"refreshOn": "",
		"redrawOn": "",
		"modalEdit": false,
		"labelPosition": "top",
		"description": "",
		"errorLabel": "",
		"tooltip": "",
		"hideLabel": false,
		"tabindex": "",
		"disabled": false,
		"autofocus": false,
		"dbIndex": false,
		"customDefaultValue": "",
		"calculateServer": false,
		"widget": {
			"type": "input"
		},
		"attributes": {},
		"validateOn": "change",
		"validate": {
			"required": false,
			"custom": "",
			"customPrivate": false,
			"strictDateValidation": false,
			"multiple": false,
			"unique": false
		},
		"conditional": {
			"show": null,
			"when": null,
			"eq": ""
		},
		"overlay": {
			"style": "",
			"left": "",
			"top": "",
			"width": "",
			"height": ""
		},
		"allowCalculateOverride": false,
		"encrypted": false,
		"showCharCount": false,
		"showWordCount": false,
		"properties": {},
		"allowMultipleMasks": false,
		"inputType": "hidden",
		"id": "ef79ye"
	}, {
		"label": "ApproverEmailId",
		"calculateValue": "if (data.privileges){\n  if(data.privileges['MANAGE_POLICY_APPROVAL_WRITE'] !== null && data.privileges['MANAGE_POLICY_APPROVAL_WRITE']){\n    value = data['userprofile'].email;\n  }\n}",
		"key": "approverEmailId",
		"type": "hidden",
		"input": true,
		"tableView": false,
		"hideOnChildrenHidden": false,
		"placeholder": "",
		"prefix": "",
		"customClass": "",
		"suffix": "",
		"multiple": false,
		"defaultValue": null,
		"protected": false,
		"unique": false,
		"persistent": true,
		"hidden": false,
		"clearOnHide": true,
		"refreshOn": "",
		"redrawOn": "",
		"modalEdit": false,
		"labelPosition": "top",
		"description": "",
		"errorLabel": "",
		"tooltip": "",
		"hideLabel": false,
		"tabindex": "",
		"disabled": false,
		"autofocus": false,
		"dbIndex": false,
		"customDefaultValue": "",
		"calculateServer": false,
		"widget": {
			"type": "input"
		},
		"attributes": {},
		"validateOn": "change",
		"validate": {
			"required": false,
			"custom": "",
			"customPrivate": false,
			"strictDateValidation": false,
			"multiple": false,
			"unique": false
		},
		"conditional": {
			"show": null,
			"when": null,
			"eq": ""
		},
		"overlay": {
			"style": "",
			"left": "",
			"top": "",
			"width": "",
			"height": ""
		},
		"allowCalculateOverride": false,
		"encrypted": false,
		"showCharCount": false,
		"showWordCount": false,
		"properties": {},
		"allowMultipleMasks": false,
		"inputType": "hidden",
		"id": "enmgiic"
	}, {
		"label": "ApproverDesignation",
		"calculateValue": "if (data.privileges){\n  if(data.privileges['MANAGE_POLICY_APPROVAL_WRITE'] !== null && data.privileges['MANAGE_POLICY_APPROVAL_WRITE']){\n    value = data['userprofile'].designation;\n  }\n}",
		"key": "approverDesignation",
		"type": "hidden",
		"input": true,
		"tableView": false,
		"hideOnChildrenHidden": false,
		"placeholder": "",
		"prefix": "",
		"customClass": "",
		"suffix": "",
		"multiple": false,
		"defaultValue": null,
		"protected": false,
		"unique": false,
		"persistent": true,
		"hidden": false,
		"clearOnHide": true,
		"refreshOn": "",
		"redrawOn": "",
		"modalEdit": false,
		"labelPosition": "top",
		"description": "",
		"errorLabel": "",
		"tooltip": "",
		"hideLabel": false,
		"tabindex": "",
		"disabled": false,
		"autofocus": false,
		"dbIndex": false,
		"customDefaultValue": "",
		"calculateServer": false,
		"widget": {
			"type": "input"
		},
		"attributes": {},
		"validateOn": "change",
		"validate": {
			"required": false,
			"custom": "",
			"customPrivate": false,
			"strictDateValidation": false,
			"multiple": false,
			"unique": false
		},
		"conditional": {
			"show": null,
			"when": null,
			"eq": ""
		},
		"overlay": {
			"style": "",
			"left": "",
			"top": "",
			"width": "",
			"height": ""
		},
		"allowCalculateOverride": false,
		"encrypted": false,
		"showCharCount": false,
		"showWordCount": false,
		"properties": {},
		"allowMultipleMasks": false,
		"inputType": "hidden",
		"id": "en4xpf"
	}, {
		"label": "Reason for Cancellation",
		"labelPosition": "top",
		"widget": "choicesjs",
		"placeholder": "--Select one--",
		"description": "",
		"tooltip": "",
		"customClass": "",
		"tabindex": "",
		"hidden": false,
		"hideLabel": false,
		"uniqueOptions": false,
		"autofocus": false,
		"disabled": false,
		"tableView": true,
		"modalEdit": false,
		"multiple": false,
		"dataSrc": "custom",
		"data": {
			"values": [{
				"value": "",
				"label": ""
			}],
			"resource": "",
			"json": "",
			"url": "",
			"custom": "var list = [{\n    \"label\": \"Non-payment of Premium\",\n    \"value\": \"nonPaymentOfPremium\"\n}, {\n    \"label\": \"PADI Membership not current\",\n    \"value\": \"padiMembershipNotCurrent\"\n}, {\n    \"label\": \"Non-Sufficient Funds\",\n    \"value\": \"nonSufficientFunds\"\n}, {\n    \"label\": \"Others\",\n    \"value\": \"others\"\n}]\nif (data['product'] == 'Dive Boat') {\n    list.push({\n        \"label\": \"Boat Sold\",\n        \"value\": \"boatSold\"\n    })\n}\nif (data['product'] == 'Dive Store') {\n    list.push({\n        \"label\": \"Store Sold\",\n        \"value\": \"storeSold\"\n    });\n    list.push({\n        \"label\": \"Business Closed\",\n        \"value\": \"Business CLosed\"\n    });\n}\nconsole.log(list);\nvalues = list"
		},
		"valueProperty": "",
		"dataType": "",
		"idPath": "id",
		"template": "<span>{{ item.label }}</span>",
		"refreshOn": "",
		"refreshOnBlur": "",
		"clearOnRefresh": false,
		"searchEnabled": true,
		"selectThreshold": 0.3,
		"readOnlyValue": false,
		"customOptions": {},
		"useExactSearch": false,
		"persistent": true,
		"protected": false,
		"dbIndex": false,
		"encrypted": false,
		"clearOnHide": true,
		"customDefaultValue": "",
		"calculateValue": "if (data.reasonForUserCancellation) {\n    value = data.reasonForUserCancellation;\n   \n}",
		"calculateServer": false,
		"allowCalculateOverride": true,
		"validateOn": "change",
		"validate": {
			"required": true,
			"customMessage": "Please select a Reason for Cancellation",
			"custom": "",
			"customPrivate": false,
			"json": "",
			"strictDateValidation": false,
			"multiple": false,
			"unique": false
		},
		"unique": false,
		"errorLabel": "",
		"key": "csrCancellationReason",
		"tags": [],
		"properties": {},
		"conditional": {
			"show": null,
			"when": null,
			"eq": "",
			"json": ""
		},
		"customConditional": "",
		"logic": [],
		"attributes": {},
		"overlay": {
			"style": "",
			"page": "",
			"left": "",
			"top": "",
			"width": "",
			"height": ""
		},
		"type": "select",
		"indexeddb": {
			"filter": {}
		},
		"selectFields": "",
		"searchField": "",
		"minSearch": 0,
		"filter": "",
		"limit": 100,
		"redrawOn": "",
		"input": true,
		"lockKey": true,
		"dataGridLabel": false,
		"prefix": "",
		"suffix": "",
		"showCharCount": false,
		"showWordCount": false,
		"allowMultipleMasks": false,
		"lazyLoad": true,
		"authenticate": false,
		"searchThreshold": 0.3,
		"fuseOptions": {
			"include": "score",
			"threshold": 0.3
		},
		"id": "emuasx",
		"defaultValue": {}
	}, {
		"label": "Reason for CSR Cancellation",
		"calculateValue": "if(data.csrCancellationReason){\n  value = data.csrCancellationReason;\n}",
		"key": "reasonforCsrCancellation",
		"type": "hidden",
		"input": true,
		"tableView": true,
		"lockKey": true,
		"placeholder": "",
		"prefix": "",
		"customClass": "",
		"suffix": "",
		"multiple": false,
		"defaultValue": null,
		"protected": false,
		"unique": false,
		"persistent": true,
		"hidden": false,
		"clearOnHide": true,
		"refreshOn": "",
		"redrawOn": "",
		"modalEdit": false,
		"labelPosition": "top",
		"description": "",
		"errorLabel": "",
		"tooltip": "",
		"hideLabel": false,
		"tabindex": "",
		"disabled": false,
		"autofocus": false,
		"dbIndex": false,
		"customDefaultValue": "",
		"calculateServer": false,
		"widget": {
			"type": "input"
		},
		"attributes": {},
		"validateOn": "change",
		"validate": {
			"required": false,
			"custom": "",
			"customPrivate": false,
			"strictDateValidation": false,
			"multiple": false,
			"unique": false
		},
		"conditional": {
			"show": null,
			"when": null,
			"eq": ""
		},
		"overlay": {
			"style": "",
			"left": "",
			"top": "",
			"width": "",
			"height": ""
		},
		"allowCalculateOverride": false,
		"encrypted": false,
		"showCharCount": false,
		"showWordCount": false,
		"properties": {},
		"allowMultipleMasks": false,
		"inputType": "hidden",
		"id": "edae6gd"
	}, {
		"label": "Others",
		"labelPosition": "top",
		"placeholder": "",
		"description": "",
		"tooltip": "",
		"prefix": "",
		"suffix": "",
		"widget": {
			"type": "input"
		},
		"editor": "",
		"autoExpand": false,
		"customClass": "others",
		"tabindex": "",
		"autocomplete": "",
		"hidden": false,
		"hideLabel": false,
		"showWordCount": false,
		"showCharCount": false,
		"autofocus": false,
		"spellcheck": true,
		"disabled": false,
		"tableView": true,
		"modalEdit": false,
		"multiple": false,
		"persistent": true,
		"inputFormat": "plain",
		"protected": false,
		"dbIndex": false,
		"case": "",
		"encrypted": false,
		"redrawOn": "",
		"clearOnHide": true,
		"customDefaultValue": "",
		"calculateValue": "if(data.othersUser){\n  value = data.othersUser\n}",
		"calculateServer": false,
		"allowCalculateOverride": false,
		"validateOn": "change",
		"validate": {
			"required": true,
			"pattern": "",
			"customMessage": "",
			"custom": "",
			"customPrivate": false,
			"json": "",
			"minLength": "",
			"maxLength": "",
			"minWords": "",
			"maxWords": "",
			"strictDateValidation": false,
			"multiple": false,
			"unique": false
		},
		"unique": false,
		"errorLabel": "",
		"key": "othersCsr",
		"tags": [],
		"properties": {},
		"conditional": {
			"show": null,
			"when": null,
			"eq": "",
			"json": ""
		},
		"customConditional": "show = data.reasonforCsrCancellation.value =='others' ? true: false;\n",
		"logic": [],
		"fixedSize": true,
		"overlay": {
			"style": "",
			"page": "",
			"left": "",
			"top": "",
			"width": "",
			"height": ""
		},
		"attributes": {},
		"type": "textarea",
		"rows": 3,
		"wysiwyg": false,
		"input": true,
		"lockKey": true,
		"refreshOn": "",
		"allowMultipleMasks": false,
		"mask": false,
		"inputType": "text",
		"inputMask": "",
		"id": "eoszrtk",
		"defaultValue": ""
	}, {
		"label": "Amount to be paid to Reinstate Policy",
		"labelPosition": "left-left",
		"placeholder": "",
		"description": "",
		"tooltip": "",
		"prefix": "$",
		"suffix": "",
		"widget": {
			"type": "input"
		},
		"customClass": "",
		"tabindex": "",
		"autocomplete": "",
		"hidden": false,
		"hideLabel": false,
		"mask": false,
		"autofocus": false,
		"spellcheck": true,
		"disabled": false,
		"tableView": true,
		"modalEdit": false,
		"multiple": false,
		"persistent": true,
		"delimiter": true,
		"requireDecimal": false,
		"inputFormat": "plain",
		"protected": false,
		"dbIndex": false,
		"encrypted": false,
		"redrawOn": "",
		"clearOnHide": false,
		"customDefaultValue": "",
		"calculateValue": "",
		"calculateServer": false,
		"allowCalculateOverride": false,
		"validateOn": "change",
		"validate": {
			"required": true,
			"customMessage": "Please enter the Amount to be paid to Reinstate Policy",
			"custom": "",
			"customPrivate": false,
			"json": "",
			"min": "",
			"max": "",
			"strictDateValidation": false,
			"multiple": false,
			"unique": false,
			"step": "any",
			"integer": ""
		},
		"errorLabel": "",
		"key": "reinstateAmount",
		"tags": [],
		"properties": {},
		"conditional": {
			"show": null,
			"when": null,
			"eq": "",
			"json": ""
		},
		"customConditional": "show = data.reasonforCsrCancellation.value == 'nonSufficientFunds' || data.reasonforCsrCancellation.value =='nonPaymentOfPremium' ? true : false;",
		"logic": [],
		"attributes": {},
		"overlay": {
			"style": "",
			"page": "",
			"left": "",
			"top": "",
			"width": "",
			"height": ""
		},
		"type": "number",
		"labelWidth": 30,
		"labelMargin": 3,
		"decimalLimit": 0,
		"input": true,
		"inputType": "number",
		"lockKey": true,
		"unique": false,
		"refreshOn": "",
		"showCharCount": false,
		"showWordCount": false,
		"allowMultipleMasks": false,
		"id": "ep5pb6o",
		"defaultValue": null
	}, {
		"label": "Effective Date",
		"labelPosition": "top",
		"displayInTimezone": "utc",
		"useLocaleSettings": false,
		"allowInput": false,
		"format": "MM-dd-yyyy",
		"placeholder": "",
		"description": "",
		"tooltip": "",
		"customClass": "",
		"tabindex": "",
		"hidden": false,
		"hideLabel": false,
		"autofocus": false,
		"disabled": false,
		"tableView": false,
		"modalEdit": false,
		"enableDate": true,
		"enableMinDateInput": false,
		"datePicker": {
			"minDate": null,
			"maxDate": null,
			"disable": "",
			"disableFunction": "",
			"disableWeekends": false,
			"disableWeekdays": false,
			"datepickerMode": "day",
			"showWeeks": true,
			"startingDay": 0,
			"initDate": "",
			"minMode": "day",
			"maxMode": "year",
			"yearRows": 4,
			"yearColumns": 5
		},
		"enableMaxDateInput": false,
		"enableTime": false,
		"timePicker": {
			"showMeridian": false,
			"hourStep": 1,
			"minuteStep": 1,
			"readonlyInput": false,
			"mousewheel": true,
			"arrowkeys": true
		},
		"multiple": false,
		"defaultValue": "",
		"defaultDate": "",
		"customOptions": {},
		"persistent": true,
		"protected": false,
		"dbIndex": false,
		"encrypted": false,
		"redrawOn": "",
		"clearOnHide": false,
		"customDefaultValue": "",
		"calculateValue": "",
		"calculateServer": false,
		"allowCalculateOverride": true,
		"validate": {
			"required": true,
			"customMessage": "",
			"custom": "if (data.cancellationDate){ \n  valid = ((moment(data.cancellationDate).diff(moment(data['start_date'])) >=0) && (moment(data.cancellationDate).diff(moment(data.end_date)) <=0)) ? true : \"Effective date should be between policy period\";\n}",
			"customPrivate": false,
			"json": "",
			"strictDateValidation": false,
			"multiple": false,
			"unique": false
		},
		"unique": false,
		"validateOn": "change",
		"errorLabel": "",
		"key": "cancellationDate",
		"tags": [],
		"properties": {},
		"conditional": {
			"show": null,
			"when": null,
			"eq": "",
			"json": ""
		},
		"customConditional": "",
		"logic": [],
		"attributes": {},
		"overlay": {
			"style": "",
			"page": "",
			"left": "",
			"top": "",
			"width": "",
			"height": ""
		},
		"type": "datetime",
		"timezone": "",
		"input": true,
		"widget": {
			"type": "calendar",
			"displayInTimezone": "utc",
			"locale": "en",
			"useLocaleSettings": false,
			"allowInput": false,
			"mode": "single",
			"enableTime": false,
			"noCalendar": false,
			"format": "MM-dd-yyyy",
			"hourIncrement": 1,
			"minuteIncrement": 1,
			"time_24hr": true,
			"minDate": null,
			"disabledDates": "",
			"disableWeekends": false,
			"disableWeekdays": false,
			"disableFunction": "",
			"maxDate": null
		},
		"hideOnChildrenHidden": false,
		"prefix": "",
		"suffix": "",
		"refreshOn": "",
		"showCharCount": false,
		"showWordCount": false,
		"allowMultipleMasks": false,
		"datepickerMode": "day",
		"id": "ennbycd"
	}, {
		"label": "CancelDate",
		"calculateValue": "value = data['cancellationDate'] ? moment(data['cancellationDate']).format(\"YYYY-MM-DD\") : moment().format(\"YYYY-MM-DD\");",
		"key": "cancelDate",
		"type": "hidden",
		"input": true,
		"tableView": false,
		"placeholder": "",
		"prefix": "",
		"customClass": "",
		"suffix": "",
		"multiple": false,
		"defaultValue": null,
		"protected": false,
		"unique": false,
		"persistent": true,
		"hidden": false,
		"clearOnHide": true,
		"refreshOn": "",
		"redrawOn": "",
		"modalEdit": false,
		"labelPosition": "top",
		"description": "",
		"errorLabel": "",
		"tooltip": "",
		"hideLabel": false,
		"tabindex": "",
		"disabled": false,
		"autofocus": false,
		"dbIndex": false,
		"customDefaultValue": "",
		"calculateServer": false,
		"widget": {
			"type": "input"
		},
		"attributes": {},
		"validateOn": "change",
		"validate": {
			"required": false,
			"custom": "",
			"customPrivate": false,
			"strictDateValidation": false,
			"multiple": false,
			"unique": false
		},
		"conditional": {
			"show": null,
			"when": null,
			"eq": ""
		},
		"overlay": {
			"style": "",
			"left": "",
			"top": "",
			"width": "",
			"height": ""
		},
		"allowCalculateOverride": false,
		"encrypted": false,
		"showCharCount": false,
		"showWordCount": false,
		"properties": {},
		"allowMultipleMasks": false,
		"inputType": "hidden",
		"id": "e18mg3x"
	}, {
		"label": "Cancellation Status:",
		"optionsLabelPosition": "right",
		"inline": false,
		"tableView": true,
		"values": [{
			"value": "approved",
			"label": "Approved",
			"shortcut": ""
		}, {
			"value": "notApproved",
			"label": "Not Approved",
			"shortcut": ""
		}],
		"validate": {
			"required": true,
			"custom": "",
			"customPrivate": false,
			"strictDateValidation": false,
			"multiple": false,
			"unique": false
		},
		"key": "cancellationStatus",
		"customConditional": "if (data.privileges){\n  show = data.privileges['MANAGE_POLICY_APPROVAL_WRITE'] != null && data.privileges['MANAGE_POLICY_APPROVAL_WRITE'] ? true: false;\n}\nelse{\n  show = false;\n}",
		"type": "radio",
		"labelWidth": 30,
		"labelMargin": 3,
		"input": true,
		"lockKey": true,
		"placeholder": "",
		"prefix": "",
		"customClass": "",
		"suffix": "",
		"multiple": false,
		"defaultValue": null,
		"protected": false,
		"unique": false,
		"persistent": true,
		"hidden": false,
		"clearOnHide": true,
		"refreshOn": "",
		"redrawOn": "",
		"modalEdit": false,
		"labelPosition": "top",
		"description": "",
		"errorLabel": "",
		"tooltip": "",
		"hideLabel": false,
		"tabindex": "",
		"disabled": false,
		"autofocus": false,
		"dbIndex": false,
		"customDefaultValue": "",
		"calculateValue": "",
		"calculateServer": false,
		"widget": null,
		"attributes": {},
		"validateOn": "change",
		"conditional": {
			"show": null,
			"when": null,
			"eq": ""
		},
		"overlay": {
			"style": "",
			"left": "",
			"top": "",
			"width": "",
			"height": ""
		},
		"allowCalculateOverride": false,
		"encrypted": false,
		"showCharCount": false,
		"showWordCount": false,
		"properties": {},
		"allowMultipleMasks": false,
		"inputType": "radio",
		"fieldSet": false,
		"id": "eswm4ld"
	}, {
		"label": "Reinstatement Criteria",
		"reorder": false,
		"addAnother": "Add More",
		"addAnotherPosition": "bottom",
		"defaultOpen": false,
		"layoutFixed": false,
		"enableRowGroups": false,
		"tableView": false,
		"defaultValue": [{
			"reason": "",
			"criteria": ""
		}],
		"validate": {
			"minLength": 1,
			"required": false,
			"custom": "",
			"customPrivate": false,
			"strictDateValidation": false,
			"multiple": false,
			"unique": false
		},
		"key": "reinstatementCriteria",
		"conditional": {
			"show": true,
			"when": "cancellationStatus",
			"eq": "approved"
		},
		"type": "datagrid",
		"input": true,
		"components": [{
			"label": "Criteria",
			"hideLabel": true,
			"tableView": true,
			"validate": {
				"required": true,
				"customMessage": "Reinstatement Criteria is required.",
				"custom": "",
				"customPrivate": false,
				"strictDateValidation": false,
				"multiple": false,
				"unique": false,
				"minLength": "",
				"maxLength": "",
				"pattern": ""
			},
			"key": "criteria",
			"type": "textfield",
			"input": true,
			"id": "elybcmq0000",
			"placeholder": "",
			"prefix": "",
			"customClass": "",
			"suffix": "",
			"multiple": false,
			"defaultValue": null,
			"protected": false,
			"unique": false,
			"persistent": true,
			"hidden": false,
			"clearOnHide": true,
			"refreshOn": "",
			"redrawOn": "",
			"modalEdit": false,
			"labelPosition": "top",
			"description": "",
			"errorLabel": "",
			"tooltip": "",
			"tabindex": "",
			"disabled": false,
			"autofocus": false,
			"dbIndex": false,
			"customDefaultValue": "",
			"calculateValue": "",
			"calculateServer": false,
			"widget": {
				"type": "input"
			},
			"attributes": {},
			"validateOn": "change",
			"conditional": {
				"show": null,
				"when": null,
				"eq": ""
			},
			"overlay": {
				"style": "",
				"left": "",
				"top": "",
				"width": "",
				"height": ""
			},
			"allowCalculateOverride": false,
			"encrypted": false,
			"showCharCount": false,
			"showWordCount": false,
			"properties": {},
			"allowMultipleMasks": false,
			"mask": false,
			"inputType": "text",
			"inputFormat": "plain",
			"inputMask": "",
			"spellcheck": true
		}],
		"placeholder": "",
		"prefix": "",
		"customClass": "",
		"suffix": "",
		"multiple": false,
		"protected": false,
		"unique": false,
		"persistent": true,
		"hidden": false,
		"clearOnHide": true,
		"refreshOn": "",
		"redrawOn": "",
		"modalEdit": false,
		"labelPosition": "top",
		"description": "",
		"errorLabel": "",
		"tooltip": "",
		"hideLabel": false,
		"tabindex": "",
		"disabled": false,
		"autofocus": false,
		"dbIndex": false,
		"customDefaultValue": "",
		"calculateValue": "",
		"calculateServer": false,
		"widget": null,
		"attributes": {},
		"validateOn": "change",
		"overlay": {
			"style": "",
			"left": "",
			"top": "",
			"width": "",
			"height": ""
		},
		"allowCalculateOverride": false,
		"encrypted": false,
		"showCharCount": false,
		"showWordCount": false,
		"properties": {},
		"allowMultipleMasks": false,
		"tree": true,
		"disableAddingRemovingRows": false,
		"id": "eu0vpj"
	}, {
		"label": "Reason for Cancel Policy Not Approved",
		"autoExpand": false,
		"tableView": true,
		"inputFormat": "plain",
		"validate": {
			"required": true,
			"customMessage": "Please Enter the reason for not Approving the Cancellation of the Policy",
			"custom": "",
			"customPrivate": false,
			"strictDateValidation": false,
			"multiple": false,
			"unique": false,
			"minLength": "",
			"maxLength": "",
			"pattern": "",
			"minWords": "",
			"maxWords": ""
		},
		"key": "reasonforRejection",
		"customConditional": "show = data.privileges['MANAGE_POLICY_APPROVAL_WRITE'] !== null && data.privileges['MANAGE_POLICY_APPROVAL_WRITE'] && data.cancellationStatus == 'notApproved' ? true : false;",
		"type": "textarea",
		"input": true,
		"lockKey": true,
		"placeholder": "",
		"prefix": "",
		"customClass": "",
		"suffix": "",
		"multiple": false,
		"defaultValue": null,
		"protected": false,
		"unique": false,
		"persistent": true,
		"hidden": false,
		"clearOnHide": true,
		"refreshOn": "",
		"redrawOn": "",
		"modalEdit": false,
		"labelPosition": "top",
		"description": "",
		"errorLabel": "",
		"tooltip": "",
		"hideLabel": false,
		"tabindex": "",
		"disabled": false,
		"autofocus": false,
		"dbIndex": false,
		"customDefaultValue": "",
		"calculateValue": "",
		"calculateServer": false,
		"widget": {
			"type": "input"
		},
		"attributes": {},
		"validateOn": "change",
		"conditional": {
			"show": null,
			"when": null,
			"eq": ""
		},
		"overlay": {
			"style": "",
			"left": "",
			"top": "",
			"width": "",
			"height": ""
		},
		"allowCalculateOverride": false,
		"encrypted": false,
		"showCharCount": false,
		"showWordCount": false,
		"properties": {},
		"allowMultipleMasks": false,
		"mask": false,
		"inputType": "text",
		"inputMask": "",
		"spellcheck": true,
		"rows": 3,
		"wysiwyg": false,
		"editor": "",
		"fixedSize": true,
		"id": "eex7hgm"
	}, {
		"label": "Reason for User Cancellation",
		"calculateValue": "if(data['userCancellationReason']){\n  value = data['userCancellationReason'];\n}",
		"key": "reasonForUserCancellation",
		"type": "hidden",
		"input": true,
		"tableView": false,
		"placeholder": "",
		"prefix": "",
		"customClass": "",
		"suffix": "",
		"multiple": false,
		"defaultValue": null,
		"protected": false,
		"unique": false,
		"persistent": true,
		"hidden": false,
		"clearOnHide": true,
		"refreshOn": "",
		"redrawOn": "",
		"modalEdit": false,
		"labelPosition": "top",
		"description": "",
		"errorLabel": "",
		"tooltip": "",
		"hideLabel": false,
		"tabindex": "",
		"disabled": false,
		"autofocus": false,
		"dbIndex": false,
		"customDefaultValue": "",
		"calculateServer": false,
		"widget": {
			"type": "input"
		},
		"attributes": {},
		"validateOn": "change",
		"validate": {
			"required": false,
			"custom": "",
			"customPrivate": false,
			"strictDateValidation": false,
			"multiple": false,
			"unique": false
		},
		"conditional": {
			"show": null,
			"when": null,
			"eq": ""
		},
		"overlay": {
			"style": "",
			"left": "",
			"top": "",
			"width": "",
			"height": ""
		},
		"allowCalculateOverride": false,
		"encrypted": false,
		"showCharCount": false,
		"showWordCount": false,
		"properties": {},
		"allowMultipleMasks": false,
		"inputType": "hidden",
		"id": "erm89v"
	}, {
		"label": "Policy Status",
		"calculateValue": "if(data.privileges && data.privileges['MANAGE_MY_POLICY_READ']){\n  value = 'Cancellation Approval Pending';\n}",
		"key": "policyStatus",
		"type": "hidden",
		"input": true,
		"tableView": false,
		"placeholder": "",
		"prefix": "",
		"customClass": "",
		"suffix": "",
		"multiple": false,
		"defaultValue": null,
		"protected": false,
		"unique": false,
		"persistent": true,
		"hidden": false,
		"clearOnHide": true,
		"refreshOn": "",
		"redrawOn": "",
		"modalEdit": false,
		"labelPosition": "top",
		"description": "",
		"errorLabel": "",
		"tooltip": "",
		"hideLabel": false,
		"tabindex": "",
		"disabled": false,
		"autofocus": false,
		"dbIndex": false,
		"customDefaultValue": "",
		"calculateServer": false,
		"widget": {
			"type": "input"
		},
		"attributes": {},
		"validateOn": "change",
		"validate": {
			"required": false,
			"custom": "",
			"customPrivate": false,
			"strictDateValidation": false,
			"multiple": false,
			"unique": false
		},
		"conditional": {
			"show": null,
			"when": null,
			"eq": ""
		},
		"overlay": {
			"style": "",
			"left": "",
			"top": "",
			"width": "",
			"height": ""
		},
		"allowCalculateOverride": false,
		"encrypted": false,
		"showCharCount": false,
		"showWordCount": false,
		"properties": {},
		"allowMultipleMasks": false,
		"inputType": "hidden",
		"id": "eioi9r"
	}, {
		"input": true,
		"label": "Submit",
		"tableView": false,
		"key": "submit",
		"type": "button",
		"placeholder": "",
		"prefix": "",
		"customClass": "",
		"suffix": "",
		"multiple": false,
		"defaultValue": null,
		"protected": false,
		"unique": false,
		"persistent": false,
		"hidden": false,
		"clearOnHide": true,
		"refreshOn": "",
		"redrawOn": "",
		"modalEdit": false,
		"labelPosition": "top",
		"description": "",
		"errorLabel": "",
		"tooltip": "",
		"hideLabel": false,
		"tabindex": "",
		"disabled": false,
		"autofocus": false,
		"dbIndex": false,
		"customDefaultValue": "",
		"calculateValue": "",
		"calculateServer": false,
		"widget": {
			"type": "input"
		},
		"attributes": {},
		"validateOn": "change",
		"validate": {
			"required": false,
			"custom": "",
			"customPrivate": false,
			"strictDateValidation": false,
			"multiple": false,
			"unique": false
		},
		"conditional": {
			"show": null,
			"when": null,
			"eq": ""
		},
		"overlay": {
			"style": "",
			"left": "",
			"top": "",
			"width": "",
			"height": ""
		},
		"allowCalculateOverride": false,
		"encrypted": false,
		"showCharCount": false,
		"showWordCount": false,
		"properties": {},
		"allowMultipleMasks": false,
		"size": "md",
		"leftIcon": "",
		"rightIcon": "",
		"block": false,
		"action": "submit",
		"disableOnInvalid": false,
		"theme": "primary",
		"dataGridLabel": true,
		"id": "eab8mf"
	}],
	"revisions": "original",
	"_vid": 131,
	"title": "Cancel Policy Generic",
	"display": "form",
	"access": [{
		"roles": ["5ce43aa430776b950569301d", "5ce43aa430776b4a5969301e", "5ce43aa430776bdfb569301f"],
		"type": "read_all"
	}],
	"submissionAccess": [],
	"settings": {},
	"properties": {},
	"name": "cancelPolicyGeneric",
	"path": "cancelpolicygeneric",
	"project": "5ce43aa430776b2aff69301c",
	"created": "2020-01-08T05:30:33.387Z",
	"modified": "2021-03-09T09:14:36.007Z",
	"machineName": "testdivehub:cancelPolicyGeneric",
	"controller": ""
}